dns_contabo.py
certbot_dns_contabo-0.2.0.dist-info/licenses/LICENSE.txt
certbot_dns_contabo-0.2.0.dist-info/METADATA
certbot_dns_contabo-0.2.0.dist-info/WHEEL
certbot_dns_contabo-0.2.0.dist-info/entry_points.txt
certbot_dns_contabo-0.2.0.dist-info/top_level.txt
certbot_dns_contabo-0.2.0.dist-info/RECORD
