Metadata-Version: 2.4
Name: certbot-dns-contabo
Version: 0.2.0
Summary: Contabo DNS Authenticator plugin for Certbot
Author-email: Lina <me@lina.sh>
License-Expression: MIT
Project-URL: Homepage, https://github.com/DAMcraft/certbot-dns-contabo
Project-URL: Bug-Tracker, https://github.com/DAMcraft/certbot-dns-contabo/issues
Keywords: certbot,dns,contabo,letsencrypt,tls,ssl,dns-01
Classifier: Development Status :: 4 - Beta
Classifier: Environment :: Plugins
Classifier: Intended Audience :: System Administrators
Classifier: Programming Language :: Python :: 3
Classifier: Programming Language :: Python :: 3.6
Classifier: Programming Language :: Python :: 3.7
Classifier: Programming Language :: Python :: 3.8
Classifier: Programming Language :: Python :: 3.9
Classifier: Programming Language :: Python :: 3.10
Classifier: Programming Language :: Python :: 3.11
Classifier: Programming Language :: Python :: 3.12
Classifier: Topic :: Internet :: WWW/HTTP
Classifier: Topic :: Security
Classifier: Topic :: System :: Systems Administration
Classifier: Topic :: Utilities
Requires-Python: >=3.5
License-File: LICENSE.txt
Requires-Dist: certbot>=2.0.0
Requires-Dist: requests
Requires-Dist: beautifulsoup4
Requires-Dist: pyotp
Dynamic: license-file
